WhiteLibrary/__init__.py
WhiteLibrary/version.py
WhiteLibrary/bin/Castle.Core.dll
WhiteLibrary/bin/TestStack.White.dll
WhiteLibrary/keywords/__init__.py
WhiteLibrary/keywords/application.py
WhiteLibrary/keywords/configuration.py
WhiteLibrary/keywords/keyboard.py
WhiteLibrary/keywords/librarycomponent.py
WhiteLibrary/keywords/mouse.py
WhiteLibrary/keywords/robotlibcore.py
WhiteLibrary/keywords/screenshot.py
WhiteLibrary/keywords/window.py
WhiteLibrary/keywords/items/__init__.py
WhiteLibrary/keywords/items/buttons.py
WhiteLibrary/keywords/items/label.py
WhiteLibrary/keywords/items/listcontrols.py
WhiteLibrary/keywords/items/listview.py
WhiteLibrary/keywords/items/menu.py
WhiteLibrary/keywords/items/progressbar.py
WhiteLibrary/keywords/items/slider.py
WhiteLibrary/keywords/items/tab.py
WhiteLibrary/keywords/items/textbox.py
WhiteLibrary/keywords/items/toolstrip.py
WhiteLibrary/keywords/items/tree.py
WhiteLibrary/keywords/items/uiitem.py
WhiteLibrary/utils/__init__.py
WhiteLibrary/utils/click.py
WhiteLibrary/utils/wait.py
robotframework_whitelibrary-1.6.0.dist-info/LICENSE
robotframework_whitelibrary-1.6.0.dist-info/METADATA
robotframework_whitelibrary-1.6.0.dist-info/WHEEL
robotframework_whitelibrary-1.6.0.dist-info/top_level.txt
robotframework_whitelibrary-1.6.0.dist-info/RECORD
