Metadata-Version: 2.1
Name: robotframework-whitelibrary
Version: 1.6.0
Summary: Windows GUI testing library for Robot Framework
Home-page: https://github.com/Omenia/robotframework-whitelibrary
Author: SALabs
Author-email: to.be.added@noexist89a887.org
License: APACHE
Platform: UNKNOWN
Classifier: License :: OSI Approved :: Apache Software License
Classifier: Programming Language :: Python :: 2
Classifier: Programming Language :: Python :: 2.7
Classifier: Programming Language :: Python :: 3
Classifier: Programming Language :: Python :: 3.5
Classifier: Programming Language :: Python :: 3.6
Requires-Dist: robotframework
Requires-Dist: pythonnet ; sys_platform == "win32"
